yahoo_finance_symbols-0.1.4.dist-info/METADATA
yahoo_finance_symbols-0.1.4.dist-info/WHEEL
yahoo_finance_symbols/__init__.py
yahoo_finance_symbols/yahoo_finance_symbols.cp312-win32.pyd
yahoo_finance_symbols-0.1.4.dist-info/RECORD
