Metadata-Version: 2.3
Name: yahoo-finance-symbols
Version: 0.1.4
Classifier: Programming Language :: Rust
Classifier: Programming Language :: Python :: Implementation :: CPython
Classifier: Programming Language :: Python :: Implementation :: PyPy
Requires-Dist: pandas ==2.2.2
Summary: A Library for scraping all Ticker Symbols from Yahoo Finance
License: MIT
Requires-Python: >=3.7
Project-URL: Source Code, https://github.com/Nnamdi-sys/yahoo-finance-symbols
